{
  "13E012EINN": {
    "datum": "09.04.2023.",
    "vreme": null,
    "naziv": "Elektroenergetske instalacije niskog napona"
  },
  "13E013EMP": {
    "datum": "08.04.2023.",
    "vreme": null,
    "naziv": "Elektromotorni pogoni"
  },
  "13E013UPE": {
    "datum": "08.04.2023.",
    "vreme": null,
    "naziv": "Upravljanje elektromotornim pogonima"
  },
  "13E014PREP": {
    "datum": null,
    "vreme": null,
    "naziv": "Praktikum iz regulacije elektromotornih pogona"
  },
  "13E023AE1": {
    "datum": "22.04.2023.",
    "vreme": null,
    "naziv": "Analiza elektroenergetskih sistema 1"
  },
  "13E023TVN1": {
    "datum": "29.04.2023.",
    "vreme": null,
    "naziv": "Tehnika visokog napona 1"
  },
  "13E024VNO": {
    "datum": null,
    "vreme": null,
    "naziv": "Visokonaponska oprema"
  },
  "13E024RZ": {
    "datum": "27.04.2023.",
    "vreme": null,
    "naziv": "Relejna zaštita"
  },
  "13E032OTE": {
    "datum": "29.04.2023.",
    "vreme": null,
    "naziv": "Osnovi telekomunikacija"
  },
  "13E032OTS": {
    "datum": "30.04.2023.",
    "vreme": null,
    "naziv": "Osnovi telekomunikacija"
  },
  "13E032T1": {
    "datum": "30.04.2023.",
    "vreme": null,
    "naziv": "Telekomunikacije 1"
  },
  "13E033AI": {
    "datum": "07.05.2023.",
    "vreme": null,
    "naziv": "Arhitektura interneta"
  },
  "13E033OTR": {
    "datum": "08.04.2023.",
    "vreme": null,
    "naziv": "Osnovi telekomunikacija"
  },
  "13E033OTF": {
    "datum": "30.04.2023.",
    "vreme": null,
    "naziv": "Osnovi telekomunikacija"
  },
  "13E033PMT": {
    "datum": null,
    "vreme": null,
    "naziv": "Principi modernih telekomunikacija"
  },
  "13E033RK": {
    "datum": "22.04.2023.",
    "vreme": null,
    "naziv": "Radio komunikacije"
  },
  "13E033T3": {
    "datum": null,
    "vreme": null,
    "naziv": "Telekomunikacije 3"
  },
  "13E033TS": {
    "datum": null,
    "vreme": null,
    "naziv": "Telekomunikacioni sistemi"
  },
  "13E034AS": {
    "datum": null,
    "vreme": null,
    "naziv": "Audio sistemi"
  },
  "13E034JMS": {
    "datum": "22.04.2023.",
    "vreme": null,
    "naziv": "Javni mobilni sistemi"
  },
  "13E034MIST": {
    "datum": null,
    "vreme": null,
    "naziv": "Modeliranje i simulacija u telekomunikacijama"
  },
  "13E034PPR": {
    "datum": "29.04.2023.",
    "vreme": null,
    "naziv": "Principi pozicioniranja u radio sistemima"
  },
  "13E034TIK": {
    "datum": "28.04.2023.",
    "vreme": null,
    "naziv": "Teorija informacija i kodovi u telekomunikacijama"
  },
  "13E042OAE": {
    "datum": "23.04.2023.",
    "vreme": null,
    "naziv": "Osnovi analogne elektronike"
  },
  "13E042OAEF": {
    "datum": "23.04.2023.",
    "vreme": null,
    "naziv": "Osnovi analogne elektronike"
  },
  "13E042OD": {
    "datum": "29.04.2023.",
    "vreme": null,
    "naziv": "Osnovi digitalne elektronike"
  },
  "13E042SIS": {
    "datum": "06.05.2023.",
    "vreme": null,
    "naziv": "Signali i sistemi"
  },
  "13E043EE": {
    "datum": "07.05.2023.",
    "vreme": null,
    "naziv": "Energetska elektronika"
  },
  "13E043LE": {
    "datum": "28.04.2023.",
    "vreme": null,
    "naziv": "Linearna elektronika"
  },
  "13E052PMS": {
    "datum": null,
    "vreme": null,
    "naziv": "Praktikum iz merno-akvizicionih sistema"
  },
  "13E052PSA": {
    "datum": "28.04.2023.",
    "vreme": null,
    "naziv": "Praktikum iz softverskih alata"
  },
  "13E052SIS": {
    "datum": "23.04.2023.",
    "vreme": null,
    "naziv": "Signali i sistemi"
  },
  "13E052SISG": {
    "datum": "23.04.2023.",
    "vreme": null,
    "naziv": "Signali i sistemi"
  },
  "13E053AES": {
    "datum": null,
    "vreme": null,
    "naziv": "Akvizicija elektrofizioloških signala"
  },
  "13E053DOSR": {
    "datum": "27.04.2023.",
    "vreme": null,
    "naziv": "Digitalna obrada signala"
  },
  "13E053MIP": {
    "datum": "22.04.2023.",
    "vreme": null,
    "naziv": "Modeliranje i identifikacija procesa"
  },
  "13E053NSU": {
    "datum": "27.04.2023.",
    "vreme": null,
    "naziv": "Nelinearni sistemi upravljanja"
  },
  "13E053SAU2": {
    "datum": "30.04.2023.",
    "vreme": null,
    "naziv": "Sistemi automatskog upravljanja 2"
  },
  "13E054ABS": {
    "datum": null,
    "vreme": null,
    "naziv": "Analiza biomedicinske slike"
  },
  "13E054VI": {
    "datum": "27.04.2023.",
    "vreme": null,
    "naziv": null
  },
  "13E054KLIN": {
    "datum": "28.04.2023.",
    "vreme": null,
    "naziv": "Kliničko inženjerstvo"
  },
  "13E062KM": {
    "datum": "28.04.2023.",
    "vreme": null,
    "naziv": "Kvantna mehanika"
  },
  "13E063EOIE": {
    "datum": null,
    "vreme": null,
    "naziv": "Ekološki obnovljivi izvori energije"
  },
  "13E063MIN": {
    "datum": "29.04.2023.",
    "vreme": null,
    "naziv": "Mikroelektronika i nanoelektronika"
  },
  "13E063MK": {
    "datum": null,
    "vreme": null,
    "naziv": "Mikroelektronska kola"
  },
  "13E063OPT": {
    "datum": "06.05.2023.",
    "vreme": null,
    "naziv": "Optičke telekomunikacije"
  },
  "13E063OTK": {
    "datum": "06.05.2023.",
    "vreme": null,
    "naziv": "Optoelektronske telekomunikacione komponente"
  },
  "13E063SP": {
    "datum": null,
    "vreme": null,
    "naziv": "Senzori i pretvarači"
  },
  "13E064DZZ": {
    "datum": null,
    "vreme": null,
    "naziv": "Dozimetrija i zaštita od zračenja"
  },
  "13E064MEMS": {
    "datum": "27.04.2023.",
    "vreme": null,
    "naziv": "Mikroelektromehanički sistemi"
  },
  "13E072OEM": {
    "datum": "09.04.2023.",
    "vreme": null,
    "naziv": "Elektromagnetika"
  },
  "13E072TEM": {
    "datum": "09.04.2023.",
    "vreme": null,
    "naziv": "Elektromagnetika"
  },
  "13E081PM2": {
    "datum": null,
    "vreme": null,
    "naziv": "Praktikum iz matematike 2"
  },
  "13E082VIS": {
    "datum": "08.04.2023.",
    "vreme": null,
    "naziv": "Verovatnoća i statistika"
  },
  "13E082VISR": {
    "datum": "08.04.2023.",
    "vreme": null,
    "naziv": "Verovatnoća i statistika"
  },
  "13E082VIST": {
    "datum": "08.04.2023.",
    "vreme": null,
    "naziv": "Verovatnoća i statistika"
  },
  "13E082VS": {
    "datum": "08.04.2023.",
    "vreme": null,
    "naziv": "Verovatnoća i statistika"
  },
  "13E082DIF": {
    "datum": "27.04.2023.",
    "vreme": null,
    "naziv": "Diferencijalne jednačine"
  },
  "13E112AR": {
    "datum": "06.05.2023.",
    "vreme": null,
    "naziv": "Arhitektura računara"
  },
  "13E112OO2": {
    "datum": "22.04.2023.",
    "vreme": null,
    "naziv": "Objektno-orijentisano programiranje 2"
  },
  "13E112OS1": {
    "datum": "07.05.2023.",
    "vreme": null,
    "naziv": "Operativni sistemi 1"
  },
  "13E112RM1": {
    "datum": null,
    "vreme": null,
    "naziv": null
  },
  "13E113AOR2": {
    "datum": null,
    "vreme": null,
    "naziv": "Arhitektura i organizacija računara 2"
  },
  "13E113BP": {
    "datum": "29.04.2023.",
    "vreme": null,
    "naziv": "Baze podataka"
  },
  "13E113ZP": {
    "datum": "09.04.2023.",
    "vreme": null,
    "naziv": null
  },
  "13E113PIA": {
    "datum": "28.04.2023.",
    "vreme": null,
    "naziv": "Programiranje internet aplikacija"
  },
  "13E113USP": {
    "datum": "22.04.2023.",
    "vreme": null,
    "naziv": "Upravljanje softverskim projektima"
  },
  "13E114IEP": {
    "datum": "06.05.2023.",
    "vreme": null,
    "naziv": "Infrastruktura za elektronsko poslovanje"
  },
  "13E114IS1": {
    "datum": "08.04.2023.",
    "vreme": null,
    "naziv": "Informacioni sistemi 1"
  },
  "13E114PRS": {
    "datum": "29.04.2023.",
    "vreme": null,
    "naziv": "Performanse računarskih sistema"
  },
  "13E114RG": {
    "datum": null,
    "vreme": null,
    "naziv": null
  },
  "13E114SAB": {
    "datum": "07.05.2023.",
    "vreme": null,
    "naziv": "Softverski alati baza podataka"
  },
  "13M011EAE": {
    "datum": null,
    "vreme": null,
    "naziv": "Elektroenergetski aspekti energetske efikasnosti zgrada"
  },
  "13M031BM": {
    "datum": null,
    "vreme": null,
    "naziv": null
  },
  "13M031BSM": {
    "datum": null,
    "vreme": null,
    "naziv": null
  },
  "13M034JMS": {
    "datum": "22.04.2023.",
    "vreme": null,
    "naziv": "Javne mobilne mreže"
  },
  "13M034PPR": {
    "datum": "29.04.2023.",
    "vreme": null,
    "naziv": "Pozicioniranje u mobilnim mrežama"
  },
  "13M051TOBS": {
    "datum": null,
    "vreme": null,
    "naziv": "Tehnike obrade biomedicinskih signala"
  },
  "13M054ABS": {
    "datum": null,
    "vreme": null,
    "naziv": "Obrada medicinske slike"
  },
  "13M054KLIN": {
    "datum": "28.04.2023.",
    "vreme": null,
    "naziv": "Klinička instrumentacija"
  },
  "13M111IS2": {
    "datum": "08.04.2023.",
    "vreme": null,
    "naziv": "Informacioni sistemi 2"
  },
  "13M113PIA": {
    "datum": "28.04.2023.",
    "vreme": null,
    "naziv": "Programiranje veb aplikacija"
  },
  "13M114RG": {
    "datum": null,
    "vreme": null,
    "naziv": "Interaktivna računarska grafika"
  },
  "13M114SAB": {
    "datum": "07.05.2023.",
    "vreme": null,
    "naziv": "Alati za programiranje baza podataka"
  },
  "19E012EINN": {
    "datum": "09.04.2023.",
    "vreme": null,
    "naziv": "Elektroenergetske instalacije niskog napona"
  },
  "19E013EP1": {
    "datum": null,
    "vreme": null,
    "naziv": "Energetski pretvarači 1"
  },
  "19E023AE1": {
    "datum": "22.04.2023.",
    "vreme": null,
    "naziv": "Analiza elektroenergetskih sistema 1"
  },
  "19E023TVN1": {
    "datum": "29.04.2023.",
    "vreme": null,
    "naziv": "Tehnika visokog napona 1"
  },
  "19E024VNO": {
    "datum": null,
    "vreme": null,
    "naziv": "Visokonaponska oprema"
  },
  "19E024RZ": {
    "datum": "27.04.2023.",
    "vreme": null,
    "naziv": "Relejna zaštita"
  },
  "19E032AIKS": {
    "datum": "28.04.2023.",
    "vreme": null,
    "naziv": "Arhitektura informaciono-komunikacionih sistema"
  },
  "19E032EM": {
    "datum": null,
    "vreme": null,
    "naziv": "Električna merenja"
  },
  "19E032OTE": {
    "datum": "29.04.2023.",
    "vreme": null,
    "naziv": "Osnovi telekomunikacija"
  },
  "19E032OTF": {
    "datum": "30.04.2023.",
    "vreme": null,
    "naziv": "Osnovi telekomunikacija"
  },
  "19E032PSA2": {
    "datum": null,
    "vreme": null,
    "naziv": "Praktikum softverski alati 2"
  },
  "19E032TM": {
    "datum": "22.04.2023.",
    "vreme": null,
    "naziv": "Telekomunikacione mreže"
  },
  "19E033KT": {
    "datum": "08.04.2023.",
    "vreme": null,
    "naziv": "Komunikacione tehnologije"
  },
  "19E034AI": {
    "datum": "07.05.2023.",
    "vreme": null,
    "naziv": "Arhitektura interneta"
  },
  "19E042AE1": {
    "datum": "23.04.2023.",
    "vreme": null,
    "naziv": "Analogna elektronika 1"
  },
  "19E042DE2": {
    "datum": "27.04.2023.",
    "vreme": null,
    "naziv": "Digitalna elektronika 2"
  },
  "19E042SIS": {
    "datum": "06.05.2023.",
    "vreme": null,
    "naziv": "Signali i sistemi"
  },
  "19E061F2": {
    "datum": "06.05.2023.",
    "vreme": null,
    "naziv": "Fizika 2"
  },
  "19E063DMJ": {
    "datum": null,
    "vreme": null,
    "naziv": "Detekcija i merenje jonizujućeg zračenja"
  },
  "19E063RNMT": {
    "datum": null,
    "vreme": null,
    "naziv": "Radiološka i nuklearna medicinska tehnika"
  },
  "19E064EOIE": {
    "datum": null,
    "vreme": null,
    "naziv": "Ekološki obnovljivi izvori energije"
  },
  "19E071OE2": {
    "datum": "23.04.2023.",
    "vreme": null,
    "naziv": "Osnovi elektrotehnike 2"
  },
  "19E081MM2": {
    "datum": "07.05.2023.",
    "vreme": null,
    "naziv": "Matematika 2"
  },
  "19E111ORT": {
    "datum": "06.05.2023.",
    "vreme": null,
    "naziv": "Osnovi računarske tehnike"
  },
  "19E111P2": {
    "datum": "09.04.2023.",
    "vreme": null,
    "naziv": "Programiranje 2"
  },
  "19E112BPO": {
    "datum": "29.04.2023.",
    "vreme": null,
    "naziv": "Baze podataka"
  },
  "19M014VMP": {
    "datum": null,
    "vreme": null,
    "naziv": "Regulisani višemotorni pogoni"
  },
  "19M024VNO": {
    "datum": null,
    "vreme": null,
    "naziv": "Ispitivanje visokonaponske opreme"
  },
  "19M034AI": {
    "datum": "07.05.2023.",
    "vreme": null,
    "naziv": "Arhitektura savremenog interneta"
  }
}